{"data":[{"image":"https:\/\/dbrjbx3wy4reb.cloudfront.net\/memes\/21\/OUrHScuYBs3hnKwHC4LMFgUzFWg6gpIBfmQhy0M8.jpg","meta_desc":"I came in like a reaching ball. Adolf Hitler. .. History Memes.","page_title":"I came in like a reaching ball","title":"1628757479000","slug":"i-came-in-like-a-reaching-ball","post_upvotes":2483,"tags":[{"name":"Adolf Hitler","slug":"adolf-hitler","title":null}],"categories":{"name":"History","slug":"history","image":"https:\/\/dbrjbx3wy4reb.cloudfront.net\/categories\/aQ6v9Y2bUScUsckpAaZQQ0aTsRcNgRUvBHZ3pvB4.webp"}},{"image":"https:\/\/dbrjbx3wy4reb.cloudfront.net\/memes\/17\/SNnI1vOjmzs1rAMKccRXi77mp47DhZC6DbxTjZz2.jpg","meta_desc":"Quarantine mood. Coronavirus Memes.","page_title":"Quarantine mood - Coronavirus","title":"Quarantine mood","slug":"quarantine-mood-coronavirus","post_upvotes":2483,"tags":[],"categories":{"name":"Coronavirus","slug":"coronavirus","image":"https:\/\/dbrjbx3wy4reb.cloudfront.net\/categories\/M7CWvepTslsXFG28LuT8oeNoKZIvDQ3bOR7bhVbK.webp"}},{"image":"https:\/\/dbrjbx3wy4reb.cloudfront.net\/memes\/17\/Npas2xtxqwqvbjwpzceQJ1p1xDk37G5uqckeK5GH.jpg","meta_desc":"Rebecca Black now. Rebecaa Black. . Celebrity Memes.","page_title":"Rebecca Black now - Rebecaa Black","title":"Rebecca Black now","slug":"rebecca-black-now-rebecaa-black","post_upvotes":2482,"tags":[{"name":"Rebecaa Black","slug":"rebecaa-black","title":null}],"categories":{"name":"Celebrity","slug":"celebrity","image":"https:\/\/dbrjbx3wy4reb.cloudfront.net\/categories\/ToFn5jtgQPtK7L6faxqAT9FIXDmUfgo6YaeFLLvW.webp"}},{"image":"https:\/\/dbrjbx3wy4reb.cloudfront.net\/memes\/16\/a1iYq7oNRSjSUiuAscQxSvTKFoIJL5ENW5mk0orO.jpg","meta_desc":"Oprah reveals how she manages to stay stress free at 64 Step 1 have a billion dollars.. Oprah.  Memes.","page_title":"Oprah reveals how she manages to stay stress free at 64 Step 1 have a billion dollars.","title":"Ok easy enough thanks Oprah","slug":"oprah-reveals-how-she-manages-to-stay-stress-free-at","post_upvotes":2482,"tags":[{"name":"Oprah","slug":"oprah","title":null}],"categories":{"name":"Celebrity","slug":"celebrity","image":"https:\/\/dbrjbx3wy4reb.cloudfront.net\/categories\/ToFn5jtgQPtK7L6faxqAT9FIXDmUfgo6YaeFLLvW.webp"}},{"image":"https:\/\/dbrjbx3wy4reb.cloudfront.net\/memes\/15\/ksWafnNLw5lQs2SzTElxvwLuOiHjGDE3OD95btJb.jpg","meta_desc":"Dolphins have returned to Italy Meanwhile in Egypt. Egypt,Pyramid Of Giza.  Memes.","page_title":"Dolphins have returned to Italy Meanwhile in Egypt","title":"Long live the pharaoh","slug":"dolphins-have-returned-to-italy-meanwhile-in-egypt","post_upvotes":2482,"tags":[{"name":"Egypt","slug":"egypt","title":null},{"name":"Pyramid Of Giza","slug":"pyramid-of-giza","title":null}],"categories":{"name":"Coronavirus","slug":"coronavirus","image":"https:\/\/dbrjbx3wy4reb.cloudfront.net\/categories\/M7CWvepTslsXFG28LuT8oeNoKZIvDQ3bOR7bhVbK.webp"}},{"image":"https:\/\/dbrjbx3wy4reb.cloudfront.net\/memes\/58\/mpVSIXlrKzCgJskIud3GqMPIwmN3BI08z75sbxtA.jpg","meta_desc":"Right tittie Left tittie Both titties. Ratatouille. .. Cartoons Memes.","page_title":"Right tittie Left tittie Both titties","title":"Ratatatataouille","slug":"right-tittie-left-tittie-both-titties","post_upvotes":2482,"tags":[{"name":"Ratatouille","slug":"ratatouille","title":null}],"categories":{"name":"Cartoons","slug":"cartoons","image":"https:\/\/dbrjbx3wy4reb.cloudfront.net\/categories\/T5Q9xATlUbnJAYMzil0spWgS1tjjp4njmpTypxqZ.webp"}},{"image":"https:\/\/dbrjbx3wy4reb.cloudfront.net\/memes\/59\/91MjT9dCiHQlb7upGtOAuRLZObIO3UZq7XYRZ7uq.jpg","meta_desc":"Congratulations you are being updated Windows 10 Please do not resist. Windows 10.  Memes.","page_title":"Congratulations you are being updated Windows 10 Please do not resist","title":"there you go","slug":"congratulations-you-are-being-updated-windows-10-please-do-not","post_upvotes":2482,"tags":[{"name":"Windows 10","slug":"windows-10","title":null}],"categories":{"name":"Corporate World","slug":"corporate-world","image":"https:\/\/dbrjbx3wy4reb.cloudfront.net\/categories\/waQxgQdi3lscae2KSrIovfg1jLy6akWyD4wEoDxa.webp"}},{"image":"https:\/\/dbrjbx3wy4reb.cloudfront.net\/memes\/64\/3kcILo33vwQzTdO2i3Skl4szRllwdNR7baIHGqHH.jpg","meta_desc":"Friendly reminder to check you're not holding tension in your body. Let your shoulders drop unclench your hands and jaw. Take a deep breath. Much better. Memes.","page_title":"Friendly reminder to check you're not holding tension in your body. Let your shoulders drop unclench your hands and jaw. Take a deep breath. Much better.","title":"It is Saturday after all","slug":"friendly-reminder-to-check-youre-not-holding-tension-in-your-3","post_upvotes":2482,"tags":[],"categories":{"name":"Random","slug":"random","image":"https:\/\/dbrjbx3wy4reb.cloudfront.net\/categories\/9Yd1ZdHEyQiNxtNgB09gjfD8hhmanQKQiN3YdvQ2.webp"}},{"image":"https:\/\/dbrjbx3wy4reb.cloudfront.net\/memes\/24\/lsxwPns7BRpo57VI0MSWYC49dzhi3VVArfyNMezq.jpg","meta_desc":"Is q tweet a meme no Patrick a tweet is not a meme Memes.","page_title":"Is q tweet a meme no Patrick a tweet is not a meme","title":"1639312369000","slug":"is-q-tweet-a-meme-no-patrick-a-tweet-is","post_upvotes":2482,"tags":[],"categories":{"name":"Memes With Template","slug":"memes-with-template","image":"https:\/\/dbrjbx3wy4reb.cloudfront.net\/categories\/W1Ahk1rbLZHqwe2adZ3qOsTd6UoDpALTVYUNYncC.webp"}},{"image":"https:\/\/dbrjbx3wy4reb.cloudfront.net\/memes\/39\/KLFZzf6fyJlfhSVW7MX3SBO5TTbgIgnB52kkF9vU.jpg","meta_desc":"If you play \"bring me to life\" by evanescence at exactly 115908 on new years eve the first \"wake me up\" will play at exactly midnight. start off your new year right. Evanescence.  Memes.","page_title":"If you play \"bring me to life\" by evanescence at exactly 115908 on new years eve the first \"wake me up\" will play at exactly midnight. start off your new year right","title":"Happy New Year everybody","slug":"if-you-play-bring-me-to-life-by-evanescence-at","post_upvotes":2482,"tags":[{"name":"Evanescence","slug":"evanescence","title":null}],"categories":{"name":"Festival","slug":"festival","image":"https:\/\/dbrjbx3wy4reb.cloudfront.net\/categories\/eN2s8TJ49xxoZ6XTKrpvPx9A3NfnZmygt3OfRMbV.webp"}}],"links":{"first":"http:\/\/localhost\/api\/posts?page=1","last":"http:\/\/localhost\/api\/posts?page=2452","prev":"http:\/\/localhost\/api\/posts?page=2124","next":"http:\/\/localhost\/api\/posts?page=2126"},"meta":{"current_page":2125,"from":21241,"last_page":2452,"links":[{"url":"http:\/\/localhost\/api\/posts?page=2124","label":"&laquo; Previous","active":false},{"url":"http:\/\/localhost\/api\/posts?page=1","label":"1","active":false},{"url":"http:\/\/localhost\/api\/posts?page=2","label":"2","active":false},{"url":null,"label":"...","active":false},{"url":"http:\/\/localhost\/api\/posts?page=2122","label":"2122","active":false},{"url":"http:\/\/localhost\/api\/posts?page=2123","label":"2123","active":false},{"url":"http:\/\/localhost\/api\/posts?page=2124","label":"2124","active":false},{"url":"http:\/\/localhost\/api\/posts?page=2125","label":"2125","active":true},{"url":"http:\/\/localhost\/api\/posts?page=2126","label":"2126","active":false},{"url":"http:\/\/localhost\/api\/posts?page=2127","label":"2127","active":false},{"url":"http:\/\/localhost\/api\/posts?page=2128","label":"2128","active":false},{"url":null,"label":"...","active":false},{"url":"http:\/\/localhost\/api\/posts?page=2451","label":"2451","active":false},{"url":"http:\/\/localhost\/api\/posts?page=2452","label":"2452","active":false},{"url":"http:\/\/localhost\/api\/posts?page=2126","label":"Next &raquo;","active":false}],"path":"http:\/\/localhost\/api\/posts","per_page":10,"to":21250,"total":24520}}