{"data":[{"name":"Kevin Hart","slug":"kevin-hart","title":null},{"name":"Keyboard","slug":"keyboard","title":null},{"name":"Keys","slug":"keys","title":null},{"name":"Kfc","slug":"kfc","title":null},{"name":"Khaby Lame","slug":"khaby-lame","title":null},{"name":"Khaleesi","slug":"khaleesi","title":null},{"name":"Khali","slug":"khali","title":null},{"name":"Kia","slug":"kia","title":null},{"name":"Kids","slug":"kids","title":null},{"name":"Kids Violence Is Never The Answer","slug":"kids-violence-is-never-the-answer","title":null},{"name":"Kill Bill","slug":"kill-bill","title":null},{"name":"Kim Jong","slug":"kim-jong","title":null},{"name":"Kim Jong Un","slug":"kim-jong-un","title":null},{"name":"Kim Kardashian","slug":"kim-kardashian","title":null},{"name":"Kim Possible","slug":"kim-possible","title":null},{"name":"Kim Yo-jong","slug":"kim-yo-jong","title":null},{"name":"Kindergarten","slug":"kindergarten","title":null},{"name":"King Kong","slug":"king-kong","title":null},{"name":"Kingdom Hearts","slug":"kingdom-hearts","title":null},{"name":"Kirsten Dunst","slug":"kirsten-dunst","title":null},{"name":"Kisame Hoshigaki","slug":"kisame-hoshigaki","title":null},{"name":"Kiss X Sis","slug":"kiss-x-sis","title":null},{"name":"Kissing","slug":"kissing","title":null},{"name":"Kitchen","slug":"kitchen","title":null},{"name":"Kitkat","slug":"kitkat","title":null},{"name":"Knock Knock","slug":"knock-knock","title":null},{"name":"Komodo Dragon","slug":"komodo-dragon","title":null},{"name":"Konan","slug":"konan","title":null},{"name":"Korean","slug":"korean","title":null},{"name":"Korean Jesus","slug":"korean-jesus","title":null},{"name":"Kowalski Analysis","slug":"kowalski-analysis","title":null},{"name":"Kpop","slug":"kpop","title":null},{"name":"Kratos","slug":"kratos","title":null},{"name":"Krilin","slug":"krilin","title":null},{"name":"Kristen Dunst","slug":"kristen-dunst","title":null},{"name":"Kristen Stewart","slug":"kristen-stewart","title":null},{"name":"Krysten Ritter","slug":"krysten-ritter","title":null},{"name":"Kumail Nanjiani","slug":"kumail-nanjiani","title":null},{"name":"Kung Fu Hustle","slug":"kung-fu-hustle","title":null},{"name":"Kung Fu Panda","slug":"kung-fu-panda","title":null},{"name":"Kurenai","slug":"kurenai","title":null},{"name":"Kuruma","slug":"kuruma","title":null},{"name":"Kushina Uzumaki","slug":"kushina-uzumaki","title":null},{"name":"Kylie Jenner","slug":"kylie-jenner","title":null},{"name":"Kyubi","slug":"kyubi","title":null},{"name":"L Am Limited By The Technology Of My Time","slug":"l-am-limited-by-the-technology-of-my-time","title":null},{"name":"Laboon","slug":"laboon","title":null},{"name":"Lady Gaga","slug":"lady-gaga","title":null},{"name":"Lamborghini","slug":"lamborghini","title":null},{"name":"Lan","slug":"lan","title":null},{"name":"Lan Gaming","slug":"lan-gaming","title":null},{"name":"Lan Party","slug":"lan-party","title":null},{"name":"Lana Rhoades","slug":"lana-rhoades","title":null},{"name":"Lanaku","slug":"lanaku","title":null},{"name":"Landlord","slug":"landlord","title":null},{"name":"Language","slug":"language","title":null},{"name":"Lapras","slug":"lapras","title":null},{"name":"Laptop","slug":"laptop","title":null},{"name":"Lara Croft","slug":"lara-croft","title":null},{"name":"Laser","slug":"laser","title":null},{"name":"Lawd That Ass","slug":"lawd-that-ass","title":null},{"name":"Lawyer","slug":"lawyer","title":null},{"name":"Lays","slug":"lays","title":null},{"name":"Leaning Tower Of Pisa","slug":"leaning-tower-of-pisa","title":null},{"name":"Lebanon","slug":"lebanon","title":null},{"name":"Legendary Saiyan","slug":"legendary-saiyan","title":null},{"name":"Lego","slug":"lego","title":null},{"name":"Lenovo","slug":"lenovo","title":null},{"name":"Leon The Professional","slug":"leon-the-professional","title":null},{"name":"Leonardo Dicaprio","slug":"leonardo-dicaprio","title":null},{"name":"Leopard","slug":"leopard","title":null},{"name":"Lesbian","slug":"lesbian","title":null},{"name":"Leslie Mann","slug":"leslie-mann","title":null},{"name":"Let Me Guess Your Home","slug":"let-me-guess-your-home","title":null},{"name":"Let Me In","slug":"let-me-in","title":null},{"name":"Let Them Fight","slug":"let-them-fight","title":null},{"name":"Let's Say You Don't Pay With Money","slug":"lets-say-you-dont-pay-with-money","title":null},{"name":"Levi Ackerman","slug":"levi-ackerman","title":null},{"name":"Lgbt","slug":"lgbt","title":null},{"name":"Liam Neeson","slug":"liam-neeson","title":null},{"name":"Library","slug":"library","title":null},{"name":"Libya","slug":"libya","title":null},{"name":"Lies Deception","slug":"lies-deception","title":null},{"name":"Life","slug":"life","title":null},{"name":"Lift","slug":"lift","title":null},{"name":"Lightning Mcqueen","slug":"lightning-mcqueen","title":null},{"name":"Lightsaber","slug":"lightsaber","title":null},{"name":"Ligma Balls","slug":"ligma-balls","title":null},{"name":"Like That's Ever Gonna Happen","slug":"like-thats-ever-gonna-happen","title":null},{"name":"Lil Wayne","slug":"lil-wayne","title":null},{"name":"Lily Potter","slug":"lily-potter","title":null},{"name":"Linkedin","slug":"linkedin","title":null},{"name":"Linkin Park","slug":"linkin-park","title":null},{"name":"Linux","slug":"linux","title":null},{"name":"Lion","slug":"lion","title":null},{"name":"Lionel Messi","slug":"lionel-messi","title":null},{"name":"Listen Here You Little Shit","slug":"listen-here-you-little-shit","title":null},{"name":"Little Mermaid","slug":"little-mermaid","title":null},{"name":"Liv Tyler","slug":"liv-tyler","title":null},{"name":"Live Your Life","slug":"live-your-life","title":null},{"name":"Lizard","slug":"lizard","title":null},{"name":"Lobster","slug":"lobster","title":null},{"name":"Logan Paul","slug":"logan-paul","title":null},{"name":"Loki","slug":"loki","title":null},{"name":"Lola Bunny","slug":"lola-bunny","title":null},{"name":"Loli","slug":"loli","title":null},{"name":"London","slug":"london","title":null},{"name":"Look How They Massacred My Boy","slug":"look-how-they-massacred-my-boy","title":null},{"name":"Looney Tunes","slug":"looney-tunes","title":null},{"name":"Loony Toons","slug":"loony-toons","title":null},{"name":"Lord Of The Rings","slug":"lord-of-the-rings","title":null},{"name":"Lottery","slug":"lottery","title":null},{"name":"Luffy","slug":"luffy","title":null},{"name":"Luigi","slug":"luigi","title":null},{"name":"Luna Lovegood","slug":"luna-lovegood","title":null},{"name":"Lynda Carter","slug":"lynda-carter","title":null},{"name":"Macbook","slug":"macbook","title":null},{"name":"Mackenzie Bezos","slug":"mackenzie-bezos","title":null},{"name":"Mackenzie Foy","slug":"mackenzie-foy","title":null},{"name":"Macos","slug":"macos","title":null},{"name":"Madonna","slug":"madonna","title":null},{"name":"Magikarp","slug":"magikarp","title":null},{"name":"Magneto","slug":"magneto","title":null},{"name":"Mahatma Gandhi","slug":"mahatma-gandhi","title":null},{"name":"Maisie Williams","slug":"maisie-williams","title":null},{"name":"Makeup","slug":"makeup","title":null},{"name":"Malala Yousafzai","slug":"malala-yousafzai","title":null},{"name":"Malena","slug":"malena","title":null},{"name":"Man Of Culture","slug":"man-of-culture","title":null},{"name":"Man Vs Wild","slug":"man-vs-wild","title":null},{"name":"Manager","slug":"manager","title":null},{"name":"Map","slug":"map","title":null},{"name":"Marble Fox","slug":"marble-fox","title":null},{"name":"Margaery Tyrell","slug":"margaery-tyrell","title":null},{"name":"Margot Robbie","slug":"margot-robbie","title":null},{"name":"Marilyn Monroe","slug":"marilyn-monroe","title":null},{"name":"Mario","slug":"mario","title":null},{"name":"Mario Cart","slug":"mario-cart","title":null},{"name":"Marisa Tomei","slug":"marisa-tomei","title":null},{"name":"Mark Henry","slug":"mark-henry","title":null},{"name":"Mark Zuckerberg","slug":"mark-zuckerberg","title":null},{"name":"Marketing 100","slug":"marketing-100","title":null},{"name":"Marques Brownlee","slug":"marques-brownlee","title":null},{"name":"Marriage Anniversary","slug":"marriage-anniversary","title":null},{"name":"Marriage Proposal","slug":"marriage-proposal","title":null},{"name":"Mars","slug":"mars","title":null},{"name":"Martin Luther King Jr","slug":"martin-luther-king-jr","title":null},{"name":"Marvel","slug":"marvel","title":null},{"name":"Mary","slug":"mary","title":null},{"name":"Mary Elizabeth Winstead","slug":"mary-elizabeth-winstead","title":null}],"links":{"first":"http:\/\/localhost\/api\/tags?page=1","last":"http:\/\/localhost\/api\/tags?page=16","prev":"http:\/\/localhost\/api\/tags?page=7","next":"http:\/\/localhost\/api\/tags?page=9"},"meta":{"current_page":8,"from":1051,"last_page":16,"links":[{"url":"http:\/\/localhost\/api\/tags?page=7","label":"&laquo; Previous","active":false},{"url":"http:\/\/localhost\/api\/tags?page=1","label":"1","active":false},{"url":"http:\/\/localhost\/api\/tags?page=2","label":"2","active":false},{"url":null,"label":"...","active":false},{"url":"http:\/\/localhost\/api\/tags?page=5","label":"5","active":false},{"url":"http:\/\/localhost\/api\/tags?page=6","label":"6","active":false},{"url":"http:\/\/localhost\/api\/tags?page=7","label":"7","active":false},{"url":"http:\/\/localhost\/api\/tags?page=8","label":"8","active":true},{"url":"http:\/\/localhost\/api\/tags?page=9","label":"9","active":false},{"url":"http:\/\/localhost\/api\/tags?page=10","label":"10","active":false},{"url":"http:\/\/localhost\/api\/tags?page=11","label":"11","active":false},{"url":null,"label":"...","active":false},{"url":"http:\/\/localhost\/api\/tags?page=15","label":"15","active":false},{"url":"http:\/\/localhost\/api\/tags?page=16","label":"16","active":false},{"url":"http:\/\/localhost\/api\/tags?page=9","label":"Next &raquo;","active":false}],"path":"http:\/\/localhost\/api\/tags","per_page":150,"to":1200,"total":2266}}